{
  "examples": {
    "proton_matmul": {
      "example": "proton_matmul",
      "metadata": {
        "best_memory_savings_pct": 0.0,
        "best_memory_savings_ratio": 1.0,
        "best_optimization": "bm64_bn64_bk32_nw2",
        "best_optimization_file": "optimized_proton_matmul_bm64_bn64_bk32_nw2.py",
        "best_optimization_memory_mb": 414.30029296875,
        "best_optimization_speedup": 1.1617855293669772,
        "best_optimization_technique": "bm64_bn64_bk32_nw2",
        "best_optimization_time_ms": 0.17151864914906687,
        "optimization_goal": "speed"
      },
      "metrics": {
        "baseline_memory_mb": 414.30029296875,
        "baseline_p75_ms": 0.20662400126457214,
        "baseline_throughput.bytes_per_s": null,
        "baseline_throughput.custom_unit_name": null,
        "baseline_throughput.custom_unit_per_s": null,
        "baseline_throughput.goodput": null,
        "baseline_throughput.latency_ms": 0.19926788459795747,
        "baseline_throughput.requests_per_s": 5018.370130327816,
        "baseline_throughput.samples_per_s": null,
        "baseline_throughput.schemaVersion": "1.0",
        "baseline_throughput.tokens_per_s": null,
        "baseline_time_ms": 0.19926788459795747,
        "best_memory_savings_pct": 0.0,
        "best_memory_savings_ratio": 1.0,
        "best_optimized_memory_mb": 414.30029296875,
        "best_optimized_p75_ms": 0.1780479997396469,
        "best_optimized_speedup": 1.1617855293669772,
        "best_optimized_throughput.bytes_per_s": null,
        "best_optimized_throughput.custom_unit_name": null,
        "best_optimized_throughput.custom_unit_per_s": null,
        "best_optimized_throughput.goodput": null,
        "best_optimized_throughput.latency_ms": 0.17151864914906687,
        "best_optimized_throughput.requests_per_s": 5830.269798422328,
        "best_optimized_throughput.samples_per_s": null,
        "best_optimized_throughput.schemaVersion": "1.0",
        "best_optimized_throughput.tokens_per_s": null,
        "best_optimized_time_ms": 0.17151864914906687,
        "best_speedup": 1.1617855293669772,
        "is_regression": false
      },
      "provenance": {
        "git_commit": "46394dc563475242d973d1ad57d7ec221705f59b",
        "hardware_key": "4x_gb200",
        "iterations": 20,
        "profile_name": "none",
        "timestamp": "2026-02-07T13:05:42.417935",
        "warmup_iterations": 5
      },
      "type": "python"
    },
    "proton_matmul_bm128_bn128_bk32_nw8": {
      "example": "proton_matmul_bm128_bn128_bk32_nw8",
      "metadata": {
        "best_memory_savings_pct": 0.0,
        "best_memory_savings_ratio": 1.0,
        "best_optimization": "optimized_proton_matmul_bm128_bn128_bk32_nw8",
        "best_optimization_file": "optimized_proton_matmul_bm128_bn128_bk32_nw8.py",
        "best_optimization_memory_mb": 414.30029296875,
        "best_optimization_speedup": 1.054653297993369,
        "best_optimization_technique": "optimized_proton_matmul_bm128_bn128_bk32_nw8",
        "best_optimization_time_ms": 0.18409312246443466,
        "optimization_goal": "speed"
      },
      "metrics": {
        "baseline_memory_mb": 414.30029296875,
        "baseline_p75_ms": 0.19916799664497375,
        "baseline_throughput.bytes_per_s": null,
        "baseline_throughput.custom_unit_name": null,
        "baseline_throughput.custom_unit_per_s": null,
        "baseline_throughput.goodput": null,
        "baseline_throughput.latency_ms": 0.19415441874501316,
        "baseline_throughput.requests_per_s": 5150.539485342952,
        "baseline_throughput.samples_per_s": null,
        "baseline_throughput.schemaVersion": "1.0",
        "baseline_throughput.tokens_per_s": null,
        "baseline_time_ms": 0.19415441874501316,
        "best_memory_savings_pct": 0.0,
        "best_memory_savings_ratio": 1.0,
        "best_optimized_memory_mb": 414.30029296875,
        "best_optimized_p75_ms": 0.18838399648666382,
        "best_optimized_speedup": 1.054653297993369,
        "best_optimized_throughput.bytes_per_s": null,
        "best_optimized_throughput.custom_unit_name": null,
        "best_optimized_throughput.custom_unit_per_s": null,
        "best_optimized_throughput.goodput": null,
        "best_optimized_throughput.latency_ms": 0.18409312246443466,
        "best_optimized_throughput.requests_per_s": 5432.033454662013,
        "best_optimized_throughput.samples_per_s": null,
        "best_optimized_throughput.schemaVersion": "1.0",
        "best_optimized_throughput.tokens_per_s": null,
        "best_optimized_time_ms": 0.18409312246443466,
        "best_speedup": 1.054653297993369,
        "is_regression": false
      },
      "provenance": {
        "git_commit": "46394dc563475242d973d1ad57d7ec221705f59b",
        "hardware_key": "4x_gb200",
        "iterations": 20,
        "profile_name": "none",
        "timestamp": "2026-02-07T13:06:10.933717",
        "warmup_iterations": 5
      },
      "type": "python"
    },
    "proton_matmul_bm128_bn256_bk64": {
      "example": "proton_matmul_bm128_bn256_bk64",
      "metadata": {
        "best_memory_savings_pct": 0.0,
        "best_memory_savings_ratio": 1.0,
        "best_optimization": "optimized_proton_matmul_bm128_bn256_bk64",
        "best_optimization_file": "optimized_proton_matmul_bm128_bn256_bk64.py",
        "best_optimization_memory_mb": 414.30029296875,
        "best_optimization_speedup": 1.1111003943015283,
        "best_optimization_technique": "optimized_proton_matmul_bm128_bn256_bk64",
        "best_optimization_time_ms": 0.17415149451086395,
        "optimization_goal": "speed"
      },
      "metrics": {
        "baseline_memory_mb": 414.30029296875,
        "baseline_p75_ms": 0.19753600656986237,
        "baseline_throughput.bytes_per_s": null,
        "baseline_throughput.custom_unit_name": null,
        "baseline_throughput.custom_unit_per_s": null,
        "baseline_throughput.goodput": null,
        "baseline_throughput.latency_ms": 0.1934997942192214,
        "baseline_throughput.requests_per_s": 5167.964152287788,
        "baseline_throughput.samples_per_s": null,
        "baseline_throughput.schemaVersion": "1.0",
        "baseline_throughput.tokens_per_s": null,
        "baseline_time_ms": 0.1934997942192214,
        "best_memory_savings_pct": 0.0,
        "best_memory_savings_ratio": 1.0,
        "best_optimized_memory_mb": 414.30029296875,
        "best_optimized_p75_ms": 0.1804479956626892,
        "best_optimized_speedup": 1.1111003943015283,
        "best_optimized_throughput.bytes_per_s": null,
        "best_optimized_throughput.custom_unit_name": null,
        "best_optimized_throughput.custom_unit_per_s": null,
        "best_optimized_throughput.goodput": null,
        "best_optimized_throughput.latency_ms": 0.17415149451086395,
        "best_optimized_throughput.requests_per_s": 5742.127007343126,
        "best_optimized_throughput.samples_per_s": null,
        "best_optimized_throughput.schemaVersion": "1.0",
        "best_optimized_throughput.tokens_per_s": null,
        "best_optimized_time_ms": 0.17415149451086395,
        "best_speedup": 1.1111003943015283,
        "is_regression": false
      },
      "provenance": {
        "git_commit": "46394dc563475242d973d1ad57d7ec221705f59b",
        "hardware_key": "4x_gb200",
        "iterations": 20,
        "profile_name": "none",
        "timestamp": "2026-02-07T13:05:56.656321",
        "warmup_iterations": 5
      },
      "type": "python"
    },
    "proton_matmul_bm64_bn256_bk32": {
      "example": "proton_matmul_bm64_bn256_bk32",
      "metadata": {
        "best_memory_savings_pct": 0.0,
        "best_memory_savings_ratio": 1.0,
        "best_optimization": "optimized_proton_matmul_bm64_bn256_bk32",
        "best_optimization_file": "optimized_proton_matmul_bm64_bn256_bk32.py",
        "best_optimization_memory_mb": 414.30029296875,
        "best_optimization_speedup": 1.1150971731486614,
        "best_optimization_technique": "optimized_proton_matmul_bm64_bn256_bk32",
        "best_optimization_time_ms": 0.17297708344024917,
        "optimization_goal": "speed"
      },
      "metrics": {
        "baseline_memory_mb": 414.30029296875,
        "baseline_p75_ms": 0.19865599274635315,
        "baseline_throughput.bytes_per_s": null,
        "baseline_throughput.custom_unit_name": null,
        "baseline_throughput.custom_unit_per_s": null,
        "baseline_throughput.goodput": null,
        "baseline_throughput.latency_ms": 0.19288625676372198,
        "baseline_throughput.requests_per_s": 5184.402542608104,
        "baseline_throughput.samples_per_s": null,
        "baseline_throughput.schemaVersion": "1.0",
        "baseline_throughput.tokens_per_s": null,
        "baseline_time_ms": 0.19288625676372198,
        "best_memory_savings_pct": 0.0,
        "best_memory_savings_ratio": 1.0,
        "best_optimized_memory_mb": 414.30029296875,
        "best_optimized_p75_ms": 0.18003199994564056,
        "best_optimized_speedup": 1.1150971731486614,
        "best_optimized_throughput.bytes_per_s": null,
        "best_optimized_throughput.custom_unit_name": null,
        "best_optimized_throughput.custom_unit_per_s": null,
        "best_optimized_throughput.goodput": null,
        "best_optimized_throughput.latency_ms": 0.17297708344024917,
        "best_optimized_throughput.requests_per_s": 5781.1126197270305,
        "best_optimized_throughput.samples_per_s": null,
        "best_optimized_throughput.schemaVersion": "1.0",
        "best_optimized_throughput.tokens_per_s": null,
        "best_optimized_time_ms": 0.17297708344024917,
        "best_speedup": 1.1150971731486614,
        "is_regression": false
      },
      "provenance": {
        "git_commit": "46394dc563475242d973d1ad57d7ec221705f59b",
        "hardware_key": "4x_gb200",
        "iterations": 20,
        "profile_name": "none",
        "timestamp": "2026-02-07T13:06:39.469523",
        "warmup_iterations": 5
      },
      "type": "python"
    },
    "proton_matmul_bm64_bn64_bk32_nw2": {
      "example": "proton_matmul_bm64_bn64_bk32_nw2",
      "metadata": {
        "best_memory_savings_pct": 0.0,
        "best_memory_savings_ratio": 1.0,
        "best_optimization": "optimized_proton_matmul_bm64_bn64_bk32_nw2",
        "best_optimization_file": "optimized_proton_matmul_bm64_bn64_bk32_nw2.py",
        "best_optimization_memory_mb": 414.30029296875,
        "best_optimization_speedup": 1.0712351176381807,
        "best_optimization_technique": "optimized_proton_matmul_bm64_bn64_bk32_nw2",
        "best_optimization_time_ms": 0.17605495659391518,
        "optimization_goal": "speed"
      },
      "metrics": {
        "baseline_memory_mb": 414.30029296875,
        "baseline_p75_ms": 0.1927040070295334,
        "baseline_throughput.bytes_per_s": null,
        "baseline_throughput.custom_unit_name": null,
        "baseline_throughput.custom_unit_per_s": null,
        "baseline_throughput.goodput": null,
        "baseline_throughput.latency_ms": 0.1885962521376675,
        "baseline_throughput.requests_per_s": 5302.332303348431,
        "baseline_throughput.samples_per_s": null,
        "baseline_throughput.schemaVersion": "1.0",
        "baseline_throughput.tokens_per_s": null,
        "baseline_time_ms": 0.1885962521376675,
        "best_memory_savings_pct": 0.0,
        "best_memory_savings_ratio": 1.0,
        "best_optimized_memory_mb": 414.30029296875,
        "best_optimized_p75_ms": 0.18111999332904816,
        "best_optimized_speedup": 1.0712351176381807,
        "best_optimized_throughput.bytes_per_s": null,
        "best_optimized_throughput.custom_unit_name": null,
        "best_optimized_throughput.custom_unit_per_s": null,
        "best_optimized_throughput.goodput": null,
        "best_optimized_throughput.latency_ms": 0.17605495659391518,
        "best_optimized_throughput.requests_per_s": 5680.044568734182,
        "best_optimized_throughput.samples_per_s": null,
        "best_optimized_throughput.schemaVersion": "1.0",
        "best_optimized_throughput.tokens_per_s": null,
        "best_optimized_time_ms": 0.17605495659391518,
        "best_speedup": 1.0712351176381807,
        "is_regression": false
      },
      "provenance": {
        "git_commit": "46394dc563475242d973d1ad57d7ec221705f59b",
        "hardware_key": "4x_gb200",
        "iterations": 20,
        "profile_name": "none",
        "timestamp": "2026-02-07T13:06:25.165787",
        "warmup_iterations": 5
      },
      "type": "python"
    }
  },
  "hardware_key": "4x_gb200",
  "schema_version": 2
}
